{"cameraMode":{"drawMode":0,"name":"Shaded","section":"Shading Mode"},"sceneLighting":true,"audioPlay":false,"sceneViewState":{"m_AlwaysRefresh":false,"showFog":true,"showSkybox":true,"showFlares":true,"showImageEffects":true,"showParticleSystems":true,"showVisualEffectGraphs":true,"m_FxEnabled":true},"in2DMode":false,"pivot":{"x":9.325268745422364,"y":-0.9759330749511719,"z":-15.207317352294922},"rotation":{"x":0.12284600734710694,"y":0.8417233824729919,"z":-0.2156534492969513,"w":0.479483962059021},"size":4.22611141204834,"orthographic":false}